CHANGES.txt
MANIFEST.in
README.md
requirements.txt
setup.py
GeobricksGeocoding.egg-info/PKG-INFO
GeobricksGeocoding.egg-info/SOURCES.txt
GeobricksGeocoding.egg-info/dependency_links.txt
GeobricksGeocoding.egg-info/pbr.json
GeobricksGeocoding.egg-info/top_level.txt
geobricks_geocoding/__init__.py
geobricks_geocoding/__init__.pyc
geobricks_geocoding/config/__init__.py
geobricks_geocoding/config/__init__.pyc
geobricks_geocoding/config/config.py
geobricks_geocoding/config/config.pyc
geobricks_geocoding/core/__init__.py
geobricks_geocoding/core/__init__.pyc
geobricks_geocoding/core/geocoding_core.py
geobricks_geocoding/core/geocoding_core.pyc
geobricks_geocoding/rest/__init__.py
geobricks_geocoding/rest/__init__.pyc
geobricks_geocoding/rest/geocoding_main.py
geobricks_geocoding/rest/geocoding_rest.py
geobricks_geocoding/rest/geocoding_rest.pyc