Metadata-Version: 1.0
Name: GeobricksGeocoding
Version: 0.1.5
Summary: Geobricks library to manage geocoding.
Home-page: http://pypi.python.org/pypi/GeobricksGeocoding/
Author: Simone Murzilli; Guido Barbaglia
Author-email: geobrickspy@gmail.com
License: LICENSE.txt
Keywords: geobricks,geocoding,geopy,gis
Platform: UNKNOWN
